vlan_change/.env.example
vlan_change/__init__.py
vlan_change/cli.py
vlan_change/creds.py
vlan_change/vlanchange.py
vlan_change-0.1.0.dist-info/entry_points.txt
vlan_change-0.1.0.dist-info/WHEEL
vlan_change-0.1.0.dist-info/METADATA
vlan_change-0.1.0.dist-info/RECORD
