Metadata-Version: 2.1
Name: vlan-change
Version: 0.1.0
Summary: Simple program to change vlans on ports
License: MIT
Author: Angelo Poggi
Author-email: angelo.poggi@opti9tech.com
Requires-Python: >=3.9,<4.0
Classifier: License :: OSI Approved :: MIT License
Classifier: Programming Language :: Python :: 3
Classifier: Programming Language :: Python :: 3.10
Classifier: Programming Language :: Python :: 3.9
Requires-Dist: click (>=8.0.4,<9.0.0)
Requires-Dist: netmiko (>=3.4.0,<4.0.0)
Requires-Dist: python-dotenv (>=0.19.2,<0.20.0)
